papermill_kubernetes_job_progress/__init__.py
papermill_kubernetes_job_progress-0.2.dist-info/LICENSE
papermill_kubernetes_job_progress-0.2.dist-info/METADATA
papermill_kubernetes_job_progress-0.2.dist-info/WHEEL
papermill_kubernetes_job_progress-0.2.dist-info/entry_points.txt
papermill_kubernetes_job_progress-0.2.dist-info/top_level.txt
papermill_kubernetes_job_progress-0.2.dist-info/RECORD
